agent_auth/__init__.py
agent_auth/chrome_cookies.py
agent_auth/cli.py
agent_auth/client.py
agent_auth/crypto.py
agent_auth/identity.py
agent_auth/langchain.py
agent_auth/models.py
agent_auth/vault.py
agentauth_py-0.3.0.dist-info/licenses/LICENSE
agentauth_py-0.3.0.dist-info/METADATA
agentauth_py-0.3.0.dist-info/WHEEL
agentauth_py-0.3.0.dist-info/entry_points.txt
agentauth_py-0.3.0.dist-info/top_level.txt
agentauth_py-0.3.0.dist-info/RECORD
